daphne/__init__.py
daphne/__main__.py
daphne/access.py
daphne/cli.py
daphne/endpoints.py
daphne/http_protocol.py
daphne/server.py
daphne/testing.py
daphne/utils.py
daphne/ws_protocol.py
twisted/plugins/fd_endpoint.py
adam_daphne-3.0.15.dist-info/LICENSE
adam_daphne-3.0.15.dist-info/METADATA
adam_daphne-3.0.15.dist-info/WHEEL
adam_daphne-3.0.15.dist-info/entry_points.txt
adam_daphne-3.0.15.dist-info/top_level.txt
adam_daphne-3.0.15.dist-info/RECORD
