Metadata-Version: 2.1
Name: adam-daphne
Version: 3.0.15
Summary: Django ASGI (HTTP/WebSocket) server
Home-page: https://github.com/django/daphne
Author: Django Software Foundation
Author-email: foundation@djangoproject.com
License: BSD
Platform: UNKNOWN
Classifier: Development Status :: 4 - Beta
Classifier: Environment :: Web Environment
Classifier: Intended Audience :: Developers
Classifier: License :: OSI Approved :: BSD License
Classifier: Operating System :: OS Independent
Classifier: Programming Language :: Python
Classifier: Programming Language :: Python :: 3
Classifier: Programming Language :: Python :: 3.6
Classifier: Programming Language :: Python :: 3.7
Classifier: Programming Language :: Python :: 3.8
Classifier: Programming Language :: Python :: 3.9
Classifier: Programming Language :: Python :: 3.10
Classifier: Topic :: Internet :: WWW/HTTP
Requires-Python: >=3.6
Requires-Dist: twisted[tls] (>=19.7)
Requires-Dist: autobahn (>=0.18)
Requires-Dist: asgiref (<4,>=3.2.10)
Provides-Extra: tests
Requires-Dist: hypothesis ; extra == 'tests'
Requires-Dist: pytest ; extra == 'tests'
Requires-Dist: pytest-asyncio ; extra == 'tests'
